odoo/addons/product_configurator/README.md
odoo/addons/product_configurator/README.rst
odoo/addons/product_configurator/__init__.py
odoo/addons/product_configurator/__manifest__.py
odoo/addons/product_configurator/init_hook.py
odoo/addons/product_configurator/data/ir_config_parameter_data.xml
odoo/addons/product_configurator/data/ir_sequence_data.xml
odoo/addons/product_configurator/data/menu_configurable_product.xml
odoo/addons/product_configurator/data/product_attribute.xml
odoo/addons/product_configurator/demo/config_image_ids.xml
odoo/addons/product_configurator/demo/product_attribute.xml
odoo/addons/product_configurator/demo/product_config_domain.xml
odoo/addons/product_configurator/demo/product_config_lines.xml
odoo/addons/product_configurator/demo/product_config_step.xml
odoo/addons/product_configurator/demo/product_template.xml
odoo/addons/product_configurator/i18n/it.po
odoo/addons/product_configurator/i18n/product_configurator.pot
odoo/addons/product_configurator/i18n/pt.po
odoo/addons/product_configurator/models/__init__.py
odoo/addons/product_configurator/models/ir_ui_view.py
odoo/addons/product_configurator/models/product.py
odoo/addons/product_configurator/models/product_attribute.py
odoo/addons/product_configurator/models/product_config.py
odoo/addons/product_configurator/readme/CONTRIBUTORS.md
odoo/addons/product_configurator/readme/DESCRIPTION.md
odoo/addons/product_configurator/security/configurator_security.xml
odoo/addons/product_configurator/security/ir.model.access.csv
odoo/addons/product_configurator/static/description/configurable-template.png
odoo/addons/product_configurator/static/description/cover.png
odoo/addons/product_configurator/static/description/icon.png
odoo/addons/product_configurator/static/description/index.html
odoo/addons/product_configurator/static/description/odoo-community-interface.png
odoo/addons/product_configurator/static/description/odoo-enterprise-interface.png
odoo_addon_product_configurator-18.0.1.0.0.4.dist-info/METADATA
odoo_addon_product_configurator-18.0.1.0.0.4.dist-info/WHEEL
odoo_addon_product_configurator-18.0.1.0.0.4.dist-info/top_level.txt
odoo_addon_product_configurator-18.0.1.0.0.4.dist-info/RECORD
