Metadata-Version: 2.1
Name: odoo-addon-product_configurator
Version: 18.0.1.0.0.4
Requires-Python: >=3.10
Requires-Dist: mako
Requires-Dist: odoo==18.0.*
Summary: Base for product configuration interface modules
Home-page: https://github.com/OCA/product-configurator
License: AGPL-3
Author: Pledra, Odoo Community Association (OCA)
Author-email: support@odoo-community.org
Classifier: Programming Language :: Python
Classifier: Framework :: Odoo
Classifier: Framework :: Odoo :: 18.0
Classifier: License :: OSI Approved :: GNU Affero General Public License v3
Classifier: Development Status :: 4 - Beta
